ClashofClans/__init__.py
ClashofClans/main.py
ClashofClans/request.py
clashofclans_api-1.0.1.dist-info/LICENSE.md
clashofclans_api-1.0.1.dist-info/METADATA
clashofclans_api-1.0.1.dist-info/WHEEL
clashofclans_api-1.0.1.dist-info/top_level.txt
clashofclans_api-1.0.1.dist-info/RECORD
