Metadata-Version: 2.1
Name: clashofclans-api
Version: 1.0.1
Summary: A Clash of Clans API
Home-page: https://github.com/Acul747/ClashofClans-API
Author: Luca Koch
Author-email: luca.koch@aon.at
License: MIT License
Keywords: coc,clash,clashofclans
Classifier: Development Status :: 3 - Alpha
Classifier: Intended Audience :: Developers
Classifier: License :: OSI Approved :: MIT License
Classifier: Programming Language :: Python :: 3.11
Classifier: Operating System :: OS Independent
Classifier: Programming Language :: Python
Requires-Python: >=3.11
License-File: LICENSE.md
Requires-Dist: requests (~=2.28.2)
